unitexpr/__init__.py
unitexpr/_unitexpr.py
unitexpr/errors.py
unitexpr/qarray.py
unitexpr/quantity.py
unitexpr/sc_units.py
unitexpr/si_units.py
unitexpr/unit.py
unitexpr/unit_dict.py
unitexpr/unit_symbol.py
unitexpr-0.1.6.dist-info/LICENSE
unitexpr-0.1.6.dist-info/METADATA
unitexpr-0.1.6.dist-info/WHEEL
unitexpr-0.1.6.dist-info/top_level.txt
unitexpr-0.1.6.dist-info/RECORD
