Metadata-Version: 2.1
Name: unitexpr
Version: 0.1.6
Summary: Units, unit expressions, and united arrays.
Home-page: https://github.com/simphotonics/unitexpr
Author: D Reschner
Author-email: git@simphotonics.com
License: UNKNOWN
Project-URL: Bug Tracker, https://github.com/simphotonics/unitexpr/issues
Platform: UNKNOWN
Classifier: Programming Language :: Python :: 3
Classifier: License :: OSI Approved :: BSD License
Classifier: Operating System :: OS Independent
Requires-Python: >=3.8
License-File: LICENSE
Requires-Dist: lockattrs
